lambda_gateway/__init__.py
lambda_gateway/__main__.py
lambda_gateway/event_proxy.py
lambda_gateway/lambda_context.py
lambda_gateway/request_handler.py
lambda_gateway-1.1.0.dist-info/LICENSE
lambda_gateway-1.1.0.dist-info/WHEEL
lambda_gateway-1.1.0.dist-info/METADATA
lambda_gateway-1.1.0.dist-info/RECORD
